AUTHORS
LICENSE
MANIFEST.in
Makefile
README.md
requirements.development.txt
requirements.txt
setup.py
version.py
TwitterFollowBot/__init__.py
TwitterFollowBot.egg-info/PKG-INFO
TwitterFollowBot.egg-info/SOURCES.txt
TwitterFollowBot.egg-info/dependency_links.txt
TwitterFollowBot.egg-info/requires.txt
TwitterFollowBot.egg-info/top_level.txt
TwitterFollowBot.egg-info/zip-safe