Metadata-Version: 1.1
Name: TwitterFollowBot
Version: v2.0
Summary: A Python bot that automates several actions on Twitter, such as following users and favoriting tweets.
Home-page: https://github.com/rhiever/TwitterFollowBot
Author: Randal S. Olson
Author-email: rso@randalolson.com
License: GNU/GPLv3
Keywords: Twitter,followers,automation,bot
Platform: UNKNOWN
Classifier: Intended Audience :: Science/Research
Classifier: Programming Language :: Python
Classifier: Programming Language :: Python :: 2
Classifier: Programming Language :: Python :: 2.6
Classifier: Programming Language :: Python :: 2.7
Classifier: Programming Language :: Python :: 3
Classifier: Programming Language :: Python :: 3.2
Classifier: Programming Language :: Python :: 3.3
Classifier: Topic :: Internet
